gdb_plus/__init__.py
gdb_plus/gdb_plus.py
gdb_plus/utils.py
gdb_plus/extra/Inner_Debugger.py
gdb_plus/extra/Structure.py
gdb_plus/extra/setup_clang.py
gdb_plus-7.5.0.dist-info/licenses/LICENSE
gdb_plus-7.5.0.dist-info/METADATA
gdb_plus-7.5.0.dist-info/WHEEL
gdb_plus-7.5.0.dist-info/top_level.txt
gdb_plus-7.5.0.dist-info/RECORD
