Metadata-Version: 2.4
Name: gdb_plus
Version: 7.5.0
Summary: Python library to automate gdb debugging
Author: Edoardo
Project-URL: Homepage, https://github.com/Angelo942/pydbg
Project-URL: Bug Tracker, https://github.com/Angelo942/pydbg/issues
Classifier: Programming Language :: Python :: 3
Classifier: License :: OSI Approved :: GNU General Public License v3 (GPLv3)
Classifier: Operating System :: Unix
Requires-Python: >=3.8
License-File: LICENSE
Requires-Dist: pwntools>=4.5.0
Requires-Dist: capstone
Requires-Dist: clang
Dynamic: license-file
